metapaddle/__init__.py
metapaddle/app/__init__.py
metapaddle/app/detection.py
metapaddle/model_zoo/__init__.py
metapaddle/model_zoo/infer.py
metapaddle/utils/__init__.py
metapaddle/utils/benchmark_utils.py
metapaddle/utils/keypoint_preprocess.py
metapaddle/utils/picodet_postprocess.py
metapaddle/utils/preprocess.py
metapaddle/utils/utils.py
metapaddle/utils/visualize.py
meta_paddle-0.5.6.dist-info/METADATA
meta_paddle-0.5.6.dist-info/WHEEL
meta_paddle-0.5.6.dist-info/top_level.txt
meta_paddle-0.5.6.dist-info/zip-safe
meta_paddle-0.5.6.dist-info/RECORD
