Metadata-Version: 2.1
Name: meta-paddle
Version: 0.5.6
Summary: Meta Paddle Toolkit
Home-page: https://github.com/CachCheng/cvpaddle
Author: CachCheng
Author-email: tkggpdc2007@163.com
License: Apache-2.0
Platform: UNKNOWN
Requires-Dist: setuptools
Requires-Dist: opencv-python
Requires-Dist: yaml
Requires-Dist: pyyaml
Requires-Dist: numpy
Requires-Dist: pillow
Requires-Dist: scipy
